insarpy/__init__.py
insarpy/common.py
insarpy/insarpy.py
insarpy-0.0.2.dist-info/LICENSE
insarpy-0.0.2.dist-info/METADATA
insarpy-0.0.2.dist-info/WHEEL
insarpy-0.0.2.dist-info/top_level.txt
insarpy-0.0.2.dist-info/RECORD
